tgcurses/__init__.py
tgcurses/canvas/__init__.py
tgcurses/canvas/canvas.py
tgcurses/layout/__init__.py
tgcurses/layout/anchor.py
tgcurses/layout/bounds.py
tgcurses/layout/frame.py
tgcurses/ui/__init__.py
tgcurses/ui/edit_field.py
tgcurses/ui/menu.py
tgcurses/ui/test.py
tgcurses/ui/window.py
tgcurses/ui/workspace.py
tgcurses-0.9.5.dist-info/LICENSE
tgcurses-0.9.5.dist-info/METADATA
tgcurses-0.9.5.dist-info/WHEEL
tgcurses-0.9.5.dist-info/top_level.txt
tgcurses-0.9.5.dist-info/RECORD
